api_access.py
data_manager.py
genius_api.py
rapy_genius-0.0.2.dist-info/LICENSE.txt
rapy_genius-0.0.2.dist-info/METADATA
rapy_genius-0.0.2.dist-info/WHEEL
rapy_genius-0.0.2.dist-info/top_level.txt
rapy_genius-0.0.2.dist-info/RECORD
